pacoteprocessamentoimagem/combinacao.py
pacoteprocessamentoimagem/io.py
pacoteprocessamentoimagem/plot.py
pacoteprocessamentoimagem/transformacao.py
pacoteprocessamentoimagem-0.0.1.dist-info/LICENSE.txt
pacoteprocessamentoimagem-0.0.1.dist-info/METADATA
pacoteprocessamentoimagem-0.0.1.dist-info/WHEEL
pacoteprocessamentoimagem-0.0.1.dist-info/top_level.txt
pacoteprocessamentoimagem-0.0.1.dist-info/RECORD
