Metadata-Version: 2.1
Name: pacoteprocessamentoimagem
Version: 0.0.1
Summary: Pacote de leitura e processamento de imagens em python
Home-page: https://github.com/isabela-rossetti/pacote_python
Author: Isabela Rossetti
Author-email: isabelarossetti.ir@gmail.com
License: MIT License
Keywords: Imagem
License-File: LICENSE.txt
